odoo9_addon_stock_inventory_exclude_sublocation-9.0.1.0.0-py2.7-nspkg.pth
odoo9_addon_stock_inventory_exclude_sublocation-9.0.1.0.0.dist-info/top_level.txt
odoo9_addon_stock_inventory_exclude_sublocation-9.0.1.0.0.dist-info/WHEEL
odoo9_addon_stock_inventory_exclude_sublocation-9.0.1.0.0.dist-info/RECORD
odoo9_addon_stock_inventory_exclude_sublocation-9.0.1.0.0.dist-info/metadata.json
odoo9_addon_stock_inventory_exclude_sublocation-9.0.1.0.0.dist-info/DESCRIPTION.rst
odoo9_addon_stock_inventory_exclude_sublocation-9.0.1.0.0.dist-info/METADATA
odoo9_addon_stock_inventory_exclude_sublocation-9.0.1.0.0.dist-info/namespace_packages.txt
odoo_addons/stock_inventory_exclude_sublocation/__openerp__.py
odoo_addons/stock_inventory_exclude_sublocation/__init__.py
odoo_addons/stock_inventory_exclude_sublocation/README.rst
odoo_addons/stock_inventory_exclude_sublocation/models/stock_inventory.py
odoo_addons/stock_inventory_exclude_sublocation/models/__init__.py
odoo_addons/stock_inventory_exclude_sublocation/views/stock_inventory_view.xml
odoo_addons/stock_inventory_exclude_sublocation/tests/test_exclude_sublocation.py
odoo_addons/stock_inventory_exclude_sublocation/tests/__init__.py
